azure/health/deidentification/__init__.py
azure/health/deidentification/_client.py
azure/health/deidentification/_configuration.py
azure/health/deidentification/_model_base.py
azure/health/deidentification/_patch.py
azure/health/deidentification/_serialization.py
azure/health/deidentification/_vendor.py
azure/health/deidentification/_version.py
azure/health/deidentification/py.typed
azure/health/deidentification/_operations/__init__.py
azure/health/deidentification/_operations/_operations.py
azure/health/deidentification/_operations/_patch.py
azure/health/deidentification/aio/__init__.py
azure/health/deidentification/aio/_client.py
azure/health/deidentification/aio/_configuration.py
azure/health/deidentification/aio/_patch.py
azure/health/deidentification/aio/_vendor.py
azure/health/deidentification/aio/_operations/__init__.py
azure/health/deidentification/aio/_operations/_operations.py
azure/health/deidentification/aio/_operations/_patch.py
azure/health/deidentification/models/__init__.py
azure/health/deidentification/models/_enums.py
azure/health/deidentification/models/_models.py
azure/health/deidentification/models/_patch.py
azure_health_deidentification-1.0.0.dist-info/LICENSE
azure_health_deidentification-1.0.0.dist-info/METADATA
azure_health_deidentification-1.0.0.dist-info/WHEEL
azure_health_deidentification-1.0.0.dist-info/top_level.txt
azure_health_deidentification-1.0.0.dist-info/RECORD
